[
  {
    "startDate": "2021-10-23T23:00Z",
    "gameState": "Scheduled",
    "id": 401282111,
    "home": {
      "teamRank": 99,
      "currentScore": "0",
      "nameRaw": "Alabama",
      "description": ""
    },
    "away": {
      "teamRank": 99,
      "currentScore": "0",
      "nameRaw": "Tennessee",
      "description": ""
    }
  },
  {
    "startDate": "2021-10-23T16:00Z",
    "gameState": "Scheduled",
    "id": 401282112,
    "home": {
      "teamRank": 99,
      "currentScore": "0",
      "nameRaw": "Arkansas",
      "description": ""
    },
    "away": {
      "teamRank": 99,
      "currentScore": "0",
      "nameRaw": "Arkansas-Pine Bluff",
      "description": ""
    }
  },
  {
    "startDate": "2021-10-23T19:30Z",
    "gameState": "Scheduled",
    "id": 401282113,
    "home": {
      "teamRank": 99,
      "currentScore": "0",
      "nameRaw": "Ole Miss",
      "description": ""
    },
    "away": {
      "teamRank": 99,
      "currentScore": "0",
      "nameRaw": "LSU",
      "description": ""
    }
  },
  {
    "startDate": "2021-10-23T23:30Z",
    "gameState": "Scheduled",
    "id": 401282114,
    "home": {
      "teamRank": 99,
      "currentScore": "0",
      "nameRaw": "Texas A&M",
      "description": ""
    },
    "away": {
      "teamRank": 99,
      "currentScore": "0",
      "nameRaw": "South Carolina",
      "description": ""
    }
  },
  {
    "startDate": "2021-10-23T20:00Z",
    "gameState": "Scheduled",
    "id": 401282115,
    "home": {
      "teamRank": 99,
      "currentScore": "0",
      "nameRaw": "Vanderbilt",
      "description": ""
    },
    "away": {
      "teamRank": 99,
      "currentScore": "0",
      "nameRaw": "Mississippi State",
      "description": ""
    }
  },
  {
    "startDate": "2021-10-21T23:30Z",
    "gameState": "Scheduled",
    "id": 401282235,
    "home": {
      "teamRank": 99,
      "currentScore": "0",
      "nameRaw": "Charlotte",
      "description": ""
    },
    "away": {
      "teamRank": 99,
      "currentScore": "0",
      "nameRaw": "Florida Atlantic",
      "description": ""
    }
  },
  {
    "startDate": "2021-10-23T23:00Z",
    "gameState": "Scheduled",
    "id": 401282236,
    "home": {
      "teamRank": 99,
      "currentScore": "0",
      "nameRaw": "Florida International",
      "description": ""
    },
    "away": {
      "teamRank": 99,
      "currentScore": "0",
      "nameRaw": "Western Kentucky",
      "description": ""
    }
  },
  {
    "startDate": "2021-10-23T23:00Z",
    "gameState": "Scheduled",
    "id": 401282237,
    "home": {
      "teamRank": 99,
      "currentScore": "0",
      "nameRaw": "Louisiana Tech",
      "description": ""
    },
    "away": {
      "teamRank": 99,
      "currentScore": "0",
      "nameRaw": "UTSA",
      "description": ""
    }
  },
  {
    "startDate": "2021-10-23T19:30Z",
    "gameState": "Scheduled",
    "id": 401282238,
    "home": {
      "teamRank": 99,
      "currentScore": "0",
      "nameRaw": "UAB",
      "description": ""
    },
    "away": {
      "teamRank": 99,
      "currentScore": "0",
      "nameRaw": "Rice",
      "description": ""
    }
  },
  {
    "startDate": "2021-10-22T22:00Z",
    "gameState": "Scheduled",
    "id": 401282239,
    "home": {
      "teamRank": 99,
      "currentScore": "0",
      "nameRaw": "UConn",
      "description": ""
    },
    "away": {
      "teamRank": 99,
      "currentScore": "0",
      "nameRaw": "Middle Tennessee",
      "description": ""
    }
  },
  {
    "startDate": "2021-10-23T20:00Z",
    "gameState": "Scheduled",
    "id": 401282240,
    "home": {
      "teamRank": 99,
      "currentScore": "0",
      "nameRaw": "North Texas",
      "description": ""
    },
    "away": {
      "teamRank": 99,
      "currentScore": "0",
      "nameRaw": "Liberty",
      "description": ""
    }
  },
  {
    "startDate": "2021-10-23T16:00Z",
    "gameState": "Scheduled",
    "id": 401282662,
    "home": {
      "teamRank": 99,
      "currentScore": "0",
      "nameRaw": "Army",
      "description": ""
    },
    "away": {
      "teamRank": 99,
      "currentScore": "0",
      "nameRaw": "Wake Forest",
      "description": ""
    }
  },
  {
    "startDate": "2021-10-23T16:00Z",
    "gameState": "Scheduled",
    "id": 401282663,
    "home": {
      "teamRank": 99,
      "currentScore": "0",
      "nameRaw": "Florida State",
      "description": ""
    },
    "away": {
      "teamRank": 99,
      "currentScore": "0",
      "nameRaw": "UMass",
      "description": ""
    }
  },
  {
    "startDate": "2021-10-23T20:00Z",
    "gameState": "Scheduled",
    "id": 401282664,
    "home": {
      "teamRank": 99,
      "currentScore": "0",
      "nameRaw": "Louisville",
      "description": ""
    },
    "away": {
      "teamRank": 99,
      "currentScore": "0",
      "nameRaw": "Boston College",
      "description": ""
    }
  },
  {
    "startDate": "2021-10-23T23:30Z",
    "gameState": "Scheduled",
    "id": 401282665,
    "home": {
      "teamRank": 99,
      "currentScore": "0",
      "nameRaw": "Miami",
      "description": ""
    },
    "away": {
      "teamRank": 99,
      "currentScore": "0",
      "nameRaw": "NC State",
      "description": ""
    }
  },
  {
    "startDate": "2021-10-23T19:30Z",
    "gameState": "Scheduled",
    "id": 401282666,
    "home": {
      "teamRank": 99,
      "currentScore": "0",
      "nameRaw": "Pittsburgh",
      "description": ""
    },
    "away": {
      "teamRank": 99,
      "currentScore": "0",
      "nameRaw": "Clemson",
      "description": ""
    }
  },
  {
    "startDate": "2021-10-23T23:30Z",
    "gameState": "Scheduled",
    "id": 401282667,
    "home": {
      "teamRank": 99,
      "currentScore": "0",
      "nameRaw": "Virginia",
      "description": ""
    },
    "away": {
      "teamRank": 99,
      "currentScore": "0",
      "nameRaw": "Georgia Tech",
      "description": ""
    }
  },
  {
    "startDate": "2021-10-23T16:30Z",
    "gameState": "Scheduled",
    "id": 401282668,
    "home": {
      "teamRank": 99,
      "currentScore": "0",
      "nameRaw": "Virginia Tech",
      "description": ""
    },
    "away": {
      "teamRank": 99,
      "currentScore": "0",
      "nameRaw": "Syracuse",
      "description": ""
    }
  },
  {
    "startDate": "2021-10-23T23:30Z",
    "gameState": "Scheduled",
    "id": 401282709,
    "home": {
      "teamRank": 99,
      "currentScore": "0",
      "nameRaw": "Notre Dame",
      "description": ""
    },
    "away": {
      "teamRank": 99,
      "currentScore": "0",
      "nameRaw": "USC",
      "description": ""
    }
  },
  {
    "startDate": "2021-10-23T16:00Z",
    "gameState": "Scheduled",
    "id": 401282717,
    "home": {
      "teamRank": 99,
      "currentScore": "0",
      "nameRaw": "Penn State",
      "description": ""
    },
    "away": {
      "teamRank": 99,
      "currentScore": "0",
      "nameRaw": "Illinois",
      "description": ""
    }
  },
  {
    "startDate": "2021-10-23T23:30Z",
    "gameState": "Scheduled",
    "id": 401282730,
    "home": {
      "teamRank": 99,
      "currentScore": "0",
      "nameRaw": "Indiana",
      "description": ""
    },
    "away": {
      "teamRank": 99,
      "currentScore": "0",
      "nameRaw": "Ohio State",
      "description": ""
    }
  },
  {
    "startDate": "2021-10-23T19:30Z",
    "gameState": "Scheduled",
    "id": 401282767,
    "home": {
      "teamRank": 99,
      "currentScore": "0",
      "nameRaw": "Minnesota",
      "description": ""
    },
    "away": {
      "teamRank": 99,
      "currentScore": "0",
      "nameRaw": "Maryland",
      "description": ""
    }
  },
  {
    "startDate": "2021-10-23T16:00Z",
    "gameState": "Scheduled",
    "id": 401282779,
    "home": {
      "teamRank": 99,
      "currentScore": "0",
      "nameRaw": "Michigan",
      "description": ""
    },
    "away": {
      "teamRank": 99,
      "currentScore": "0",
      "nameRaw": "Northwestern",
      "description": ""
    }
  },
  {
    "startDate": "2021-10-23T19:00Z",
    "gameState": "Scheduled",
    "id": 401282821,
    "home": {
      "teamRank": 99,
      "currentScore": "0",
      "nameRaw": "Purdue",
      "description": ""
    },
    "away": {
      "teamRank": 99,
      "currentScore": "0",
      "nameRaw": "Wisconsin",
      "description": ""
    }
  },
  {
    "startDate": "2021-10-23T19:30Z",
    "gameState": "Scheduled",
    "id": 401287925,
    "home": {
      "teamRank": 99,
      "currentScore": "0",
      "nameRaw": "Iowa State",
      "description": ""
    },
    "away": {
      "teamRank": 99,
      "currentScore": "0",
      "nameRaw": "Oklahoma State",
      "description": ""
    }
  },
  {
    "startDate": "2021-10-23T16:00Z",
    "gameState": "Scheduled",
    "id": 401287926,
    "home": {
      "teamRank": 99,
      "currentScore": "0",
      "nameRaw": "Kansas",
      "description": ""
    },
    "away": {
      "teamRank": 99,
      "currentScore": "0",
      "nameRaw": "Oklahoma",
      "description": ""
    }
  },
  {
    "startDate": "2021-10-23T23:30Z",
    "gameState": "Scheduled",
    "id": 401287927,
    "home": {
      "teamRank": 99,
      "currentScore": "0",
      "nameRaw": "TCU",
      "description": ""
    },
    "away": {
      "teamRank": 99,
      "currentScore": "0",
      "nameRaw": "West Virginia",
      "description": ""
    }
  },
  {
    "startDate": "2021-10-23T04:00Z",
    "gameState": "Scheduled",
    "id": 401287928,
    "home": {
      "teamRank": 99,
      "currentScore": "0",
      "nameRaw": "Texas Tech",
      "description": ""
    },
    "away": {
      "teamRank": 99,
      "currentScore": "0",
      "nameRaw": "Kansas State",
      "description": ""
    }
  },
  {
    "startDate": "2021-10-21T23:30Z",
    "gameState": "Scheduled",
    "id": 401301025,
    "home": {
      "teamRank": 99,
      "currentScore": "0",
      "nameRaw": "SMU",
      "description": ""
    },
    "away": {
      "teamRank": 99,
      "currentScore": "0",
      "nameRaw": "Tulane",
      "description": ""
    }
  },
  {
    "startDate": "2021-10-22T23:00Z",
    "gameState": "Scheduled",
    "id": 401301026,
    "home": {
      "teamRank": 99,
      "currentScore": "0",
      "nameRaw": "UCF",
      "description": ""
    },
    "away": {
      "teamRank": 99,
      "currentScore": "0",
      "nameRaw": "Memphis",
      "description": ""
    }
  },
  {
    "startDate": "2021-10-23T16:00Z",
    "gameState": "Scheduled",
    "id": 401301027,
    "home": {
      "teamRank": 99,
      "currentScore": "0",
      "nameRaw": "Navy",
      "description": ""
    },
    "away": {
      "teamRank": 99,
      "currentScore": "0",
      "nameRaw": "Cincinnati",
      "description": ""
    }
  },
  {
    "startDate": "2021-10-23T20:00Z",
    "gameState": "Scheduled",
    "id": 401301028,
    "home": {
      "teamRank": 99,
      "currentScore": "0",
      "nameRaw": "Houston",
      "description": ""
    },
    "away": {
      "teamRank": 99,
      "currentScore": "0",
      "nameRaw": "East Carolina",
      "description": ""
    }
  },
  {
    "startDate": "2021-10-23T23:00Z",
    "gameState": "Scheduled",
    "id": 401301029,
    "home": {
      "teamRank": 99,
      "currentScore": "0",
      "nameRaw": "South Florida",
      "description": ""
    },
    "away": {
      "teamRank": 99,
      "currentScore": "0",
      "nameRaw": "Temple",
      "description": ""
    }
  },
  {
    "startDate": "2021-10-23T19:30Z",
    "gameState": "Scheduled",
    "id": 401308838,
    "home": {
      "teamRank": 99,
      "currentScore": "0",
      "nameRaw": "Ball State",
      "description": ""
    },
    "away": {
      "teamRank": 99,
      "currentScore": "0",
      "nameRaw": "Miami (OH)",
      "description": ""
    }
  },
  {
    "startDate": "2021-10-23T19:30Z",
    "gameState": "Scheduled",
    "id": 401309573,
    "home": {
      "teamRank": 99,
      "currentScore": "0",
      "nameRaw": "Toledo",
      "description": ""
    },
    "away": {
      "teamRank": 99,
      "currentScore": "0",
      "nameRaw": "Western Michigan",
      "description": ""
    }
  },
  {
    "startDate": "2021-10-23T16:00Z",
    "gameState": "Scheduled",
    "id": 401309574,
    "home": {
      "teamRank": 99,
      "currentScore": "0",
      "nameRaw": "Bowling Green",
      "description": ""
    },
    "away": {
      "teamRank": 99,
      "currentScore": "0",
      "nameRaw": "Eastern Michigan",
      "description": ""
    }
  },
  {
    "startDate": "2021-10-23T19:30Z",
    "gameState": "Scheduled",
    "id": 401309575,
    "home": {
      "teamRank": 99,
      "currentScore": "0",
      "nameRaw": "Akron",
      "description": ""
    },
    "away": {
      "teamRank": 99,
      "currentScore": "0",
      "nameRaw": "Buffalo",
      "description": ""
    }
  },
  {
    "startDate": "2021-10-23T17:00Z",
    "gameState": "Scheduled",
    "id": 401309576,
    "home": {
      "teamRank": 99,
      "currentScore": "0",
      "nameRaw": "Ohio",
      "description": ""
    },
    "away": {
      "teamRank": 99,
      "currentScore": "0",
      "nameRaw": "Kent State",
      "description": ""
    }
  },
  {
    "startDate": "2021-10-23T16:00Z",
    "gameState": "Scheduled",
    "id": 401309577,
    "home": {
      "teamRank": 99,
      "currentScore": "0",
      "nameRaw": "Central Michigan",
      "description": ""
    },
    "away": {
      "teamRank": 99,
      "currentScore": "0",
      "nameRaw": "Northern Illinois",
      "description": ""
    }
  },
  {
    "startDate": "2021-10-20T23:30Z",
    "gameState": "Scheduled",
    "id": 401309623,
    "home": {
      "teamRank": 99,
      "currentScore": "0",
      "nameRaw": "Appalachian State",
      "description": ""
    },
    "away": {
      "teamRank": 99,
      "currentScore": "0",
      "nameRaw": "Coastal Carolina",
      "description": ""
    }
  },
  {
    "startDate": "2021-10-21T23:30Z",
    "gameState": "Scheduled",
    "id": 401309624,
    "home": {
      "teamRank": 99,
      "currentScore": "0",
      "nameRaw": "Arkansas State",
      "description": ""
    },
    "away": {
      "teamRank": 99,
      "currentScore": "0",
      "nameRaw": "Louisiana",
      "description": ""
    }
  },
  {
    "startDate": "2021-10-23T18:00Z",
    "gameState": "Scheduled",
    "id": 401309625,
    "home": {
      "teamRank": 99,
      "currentScore": "0",
      "nameRaw": "Georgia State",
      "description": ""
    },
    "away": {
      "teamRank": 99,
      "currentScore": "0",
      "nameRaw": "Texas State",
      "description": ""
    }
  },
  {
    "startDate": "2021-10-23T23:00Z",
    "gameState": "Scheduled",
    "id": 401309626,
    "home": {
      "teamRank": 99,
      "currentScore": "0",
      "nameRaw": "UL Monroe",
      "description": ""
    },
    "away": {
      "teamRank": 99,
      "currentScore": "0",
      "nameRaw": "South Alabama",
      "description": ""
    }
  },
  {
    "startDate": "2021-10-23T02:30Z",
    "gameState": "Scheduled",
    "id": 401309877,
    "home": {
      "teamRank": 99,
      "currentScore": "0",
      "nameRaw": "Arizona",
      "description": ""
    },
    "away": {
      "teamRank": 99,
      "currentScore": "0",
      "nameRaw": "Washington",
      "description": ""
    }
  },
  {
    "startDate": "2021-10-23T19:30Z",
    "gameState": "Scheduled",
    "id": 401309878,
    "home": {
      "teamRank": 99,
      "currentScore": "0",
      "nameRaw": "California",
      "description": ""
    },
    "away": {
      "teamRank": 99,
      "currentScore": "0",
      "nameRaw": "Colorado",
      "description": ""
    }
  },
  {
    "startDate": "2021-10-23T19:30Z",
    "gameState": "Scheduled",
    "id": 401309879,
    "home": {
      "teamRank": 99,
      "currentScore": "0",
      "nameRaw": "UCLA",
      "description": ""
    },
    "away": {
      "teamRank": 99,
      "currentScore": "0",
      "nameRaw": "Oregon",
      "description": ""
    }
  },
  {
    "startDate": "2021-10-23T23:30Z",
    "gameState": "Scheduled",
    "id": 401309880,
    "home": {
      "teamRank": 99,
      "currentScore": "0",
      "nameRaw": "Oregon State",
      "description": ""
    },
    "away": {
      "teamRank": 99,
      "currentScore": "0",
      "nameRaw": "Utah",
      "description": ""
    }
  },
  {
    "startDate": "2021-10-23T19:30Z",
    "gameState": "Scheduled",
    "id": 401309881,
    "home": {
      "teamRank": 99,
      "currentScore": "0",
      "nameRaw": "Washington State",
      "description": ""
    },
    "away": {
      "teamRank": 99,
      "currentScore": "0",
      "nameRaw": "BYU",
      "description": ""
    }
  },
  {
    "startDate": "2021-10-23T23:00Z",
    "gameState": "Scheduled",
    "id": 401310724,
    "home": {
      "teamRank": 99,
      "currentScore": "0",
      "nameRaw": "Air Force",
      "description": ""
    },
    "away": {
      "teamRank": 99,
      "currentScore": "0",
      "nameRaw": "San Diego State",
      "description": ""
    }
  },
  {
    "startDate": "2021-10-23T01:30Z",
    "gameState": "Scheduled",
    "id": 401310725,
    "home": {
      "teamRank": 99,
      "currentScore": "0",
      "nameRaw": "Utah State",
      "description": ""
    },
    "away": {
      "teamRank": 99,
      "currentScore": "0",
      "nameRaw": "Colorado State",
      "description": ""
    }
  },
  {
    "startDate": "2021-10-23T19:30Z",
    "gameState": "Scheduled",
    "id": 401310726,
    "home": {
      "teamRank": 99,
      "currentScore": "0",
      "nameRaw": "Wyoming",
      "description": ""
    },
    "away": {
      "teamRank": 99,
      "currentScore": "0",
      "nameRaw": "New Mexico",
      "description": ""
    }
  },
  {
    "startDate": "2021-10-23T23:00Z",
    "gameState": "Scheduled",
    "id": 401310727,
    "home": {
      "teamRank": 99,
      "currentScore": "0",
      "nameRaw": "Fresno State",
      "description": ""
    },
    "away": {
      "teamRank": 99,
      "currentScore": "0",
      "nameRaw": "Nevada",
      "description": ""
    }
  },
  {
    "startDate": "2021-10-24T03:59Z",
    "gameState": "Scheduled",
    "id": 401310728,
    "home": {
      "teamRank": 99,
      "currentScore": "0",
      "nameRaw": "Hawai'i",
      "description": ""
    },
    "away": {
      "teamRank": 99,
      "currentScore": "0",
      "nameRaw": "New Mexico State",
      "description": ""
    }
  },
  {
    "startDate": "2021-10-22T03:00Z",
    "gameState": "Scheduled",
    "id": 401310729,
    "home": {
      "teamRank": 99,
      "currentScore": "0",
      "nameRaw": "UNLV",
      "description": ""
    },
    "away": {
      "teamRank": 99,
      "currentScore": "0",
      "nameRaw": "San José State",
      "description": ""
    }
  }
]
