[
  {
    "startDate": "2021-09-18T20:00Z",
    "gameState": "Scheduled",
    "id": 401282069,
    "home": {
      "teamRank": 99,
      "currentScore": "0",
      "nameRaw": "Arkansas",
      "description": ""
    },
    "away": {
      "teamRank": 99,
      "currentScore": "0",
      "nameRaw": "Georgia Southern",
      "description": ""
    }
  },
  {
    "startDate": "2021-09-18T23:30Z",
    "gameState": "Scheduled",
    "id": 401282070,
    "home": {
      "teamRank": 99,
      "currentScore": "0",
      "nameRaw": "Penn State",
      "description": ""
    },
    "away": {
      "teamRank": 99,
      "currentScore": "0",
      "nameRaw": "Auburn",
      "description": ""
    }
  },
  {
    "startDate": "2021-09-18T19:30Z",
    "gameState": "Scheduled",
    "id": 401282071,
    "home": {
      "teamRank": 99,
      "currentScore": "0",
      "nameRaw": "Florida",
      "description": ""
    },
    "away": {
      "teamRank": 99,
      "currentScore": "0",
      "nameRaw": "Alabama",
      "description": ""
    }
  },
  {
    "startDate": "2021-09-18T23:00Z",
    "gameState": "Scheduled",
    "id": 401282072,
    "home": {
      "teamRank": 99,
      "currentScore": "0",
      "nameRaw": "Georgia",
      "description": ""
    },
    "away": {
      "teamRank": 99,
      "currentScore": "0",
      "nameRaw": "South Carolina",
      "description": ""
    }
  },
  {
    "startDate": "2021-09-18T16:00Z",
    "gameState": "Scheduled",
    "id": 401282073,
    "home": {
      "teamRank": 99,
      "currentScore": "0",
      "nameRaw": "Kentucky",
      "description": ""
    },
    "away": {
      "teamRank": 99,
      "currentScore": "0",
      "nameRaw": "Chattanooga",
      "description": ""
    }
  },
  {
    "startDate": "2021-09-18T23:30Z",
    "gameState": "Scheduled",
    "id": 401282074,
    "home": {
      "teamRank": 99,
      "currentScore": "0",
      "nameRaw": "LSU",
      "description": ""
    },
    "away": {
      "teamRank": 99,
      "currentScore": "0",
      "nameRaw": "Central Michigan",
      "description": ""
    }
  },
  {
    "startDate": "2021-09-19T00:00Z",
    "gameState": "Scheduled",
    "id": 401282075,
    "home": {
      "teamRank": 99,
      "currentScore": "0",
      "nameRaw": "Ole Miss",
      "description": ""
    },
    "away": {
      "teamRank": 99,
      "currentScore": "0",
      "nameRaw": "Tulane",
      "description": ""
    }
  },
  {
    "startDate": "2021-09-18T20:00Z",
    "gameState": "Scheduled",
    "id": 401282076,
    "home": {
      "teamRank": 99,
      "currentScore": "0",
      "nameRaw": "Memphis",
      "description": ""
    },
    "away": {
      "teamRank": 99,
      "currentScore": "0",
      "nameRaw": "Mississippi State",
      "description": ""
    }
  },
  {
    "startDate": "2021-09-18T16:00Z",
    "gameState": "Scheduled",
    "id": 401282077,
    "home": {
      "teamRank": 99,
      "currentScore": "0",
      "nameRaw": "Missouri",
      "description": ""
    },
    "away": {
      "teamRank": 99,
      "currentScore": "0",
      "nameRaw": "Southeast Missouri State",
      "description": ""
    }
  },
  {
    "startDate": "2021-09-18T16:00Z",
    "gameState": "Scheduled",
    "id": 401282078,
    "home": {
      "teamRank": 99,
      "currentScore": "0",
      "nameRaw": "Tennessee",
      "description": ""
    },
    "away": {
      "teamRank": 99,
      "currentScore": "0",
      "nameRaw": "Tennessee Tech",
      "description": ""
    }
  },
  {
    "startDate": "2021-09-18T16:00Z",
    "gameState": "Scheduled",
    "id": 401282079,
    "home": {
      "teamRank": 99,
      "currentScore": "0",
      "nameRaw": "Texas A&M",
      "description": ""
    },
    "away": {
      "teamRank": 99,
      "currentScore": "0",
      "nameRaw": "New Mexico",
      "description": ""
    }
  },
  {
    "startDate": "2021-09-19T00:00Z",
    "gameState": "Scheduled",
    "id": 401282080,
    "home": {
      "teamRank": 99,
      "currentScore": "0",
      "nameRaw": "Vanderbilt",
      "description": ""
    },
    "away": {
      "teamRank": 99,
      "currentScore": "0",
      "nameRaw": "Stanford",
      "description": ""
    }
  },
  {
    "startDate": "2021-09-18T22:00Z",
    "gameState": "Scheduled",
    "id": 401282194,
    "home": {
      "teamRank": 99,
      "currentScore": "0",
      "nameRaw": "UTSA",
      "description": ""
    },
    "away": {
      "teamRank": 99,
      "currentScore": "0",
      "nameRaw": "Middle Tennessee",
      "description": ""
    }
  },
  {
    "startDate": "2021-09-18T23:30Z",
    "gameState": "Scheduled",
    "id": 401282195,
    "home": {
      "teamRank": 99,
      "currentScore": "0",
      "nameRaw": "North Texas",
      "description": ""
    },
    "away": {
      "teamRank": 99,
      "currentScore": "0",
      "nameRaw": "UAB",
      "description": ""
    }
  },
  {
    "startDate": "2021-09-18T23:00Z",
    "gameState": "Scheduled",
    "id": 401282196,
    "home": {
      "teamRank": 99,
      "currentScore": "0",
      "nameRaw": "Georgia State",
      "description": ""
    },
    "away": {
      "teamRank": 99,
      "currentScore": "0",
      "nameRaw": "Charlotte",
      "description": ""
    }
  },
  {
    "startDate": "2021-09-18T23:00Z",
    "gameState": "Scheduled",
    "id": 401282197,
    "home": {
      "teamRank": 99,
      "currentScore": "0",
      "nameRaw": "Texas Tech",
      "description": ""
    },
    "away": {
      "teamRank": 99,
      "currentScore": "0",
      "nameRaw": "Florida International",
      "description": ""
    }
  },
  {
    "startDate": "2021-09-18T22:00Z",
    "gameState": "Scheduled",
    "id": 401282198,
    "home": {
      "teamRank": 99,
      "currentScore": "0",
      "nameRaw": "Florida Atlantic",
      "description": ""
    },
    "away": {
      "teamRank": 99,
      "currentScore": "0",
      "nameRaw": "Fordham",
      "description": ""
    }
  },
  {
    "startDate": "2021-09-18T19:30Z",
    "gameState": "Scheduled",
    "id": 401282199,
    "home": {
      "teamRank": 99,
      "currentScore": "0",
      "nameRaw": "Louisiana Tech",
      "description": ""
    },
    "away": {
      "teamRank": 99,
      "currentScore": "0",
      "nameRaw": "SMU",
      "description": ""
    }
  },
  {
    "startDate": "2021-09-18T22:00Z",
    "gameState": "Scheduled",
    "id": 401282200,
    "home": {
      "teamRank": 99,
      "currentScore": "0",
      "nameRaw": "Marshall",
      "description": ""
    },
    "away": {
      "teamRank": 99,
      "currentScore": "0",
      "nameRaw": "East Carolina",
      "description": ""
    }
  },
  {
    "startDate": "2021-09-18T22:00Z",
    "gameState": "Scheduled",
    "id": 401282201,
    "home": {
      "teamRank": 99,
      "currentScore": "0",
      "nameRaw": "Liberty",
      "description": ""
    },
    "away": {
      "teamRank": 99,
      "currentScore": "0",
      "nameRaw": "Old Dominion",
      "description": ""
    }
  },
  {
    "startDate": "2021-09-19T00:00Z",
    "gameState": "Scheduled",
    "id": 401282202,
    "home": {
      "teamRank": 99,
      "currentScore": "0",
      "nameRaw": "Texas",
      "description": ""
    },
    "away": {
      "teamRank": 99,
      "currentScore": "0",
      "nameRaw": "Rice",
      "description": ""
    }
  },
  {
    "startDate": "2021-09-18T23:00Z",
    "gameState": "Scheduled",
    "id": 401282203,
    "home": {
      "teamRank": 99,
      "currentScore": "0",
      "nameRaw": "Southern Mississippi",
      "description": ""
    },
    "away": {
      "teamRank": 99,
      "currentScore": "0",
      "nameRaw": "Troy",
      "description": ""
    }
  },
  {
    "startDate": "2021-09-17T23:30Z",
    "gameState": "Scheduled",
    "id": 401282626,
    "home": {
      "teamRank": 99,
      "currentScore": "0",
      "nameRaw": "Louisville",
      "description": ""
    },
    "away": {
      "teamRank": 99,
      "currentScore": "0",
      "nameRaw": "UCF",
      "description": ""
    }
  },
  {
    "startDate": "2021-09-18T19:30Z",
    "gameState": "Scheduled",
    "id": 401282627,
    "home": {
      "teamRank": 99,
      "currentScore": "0",
      "nameRaw": "Clemson",
      "description": ""
    },
    "away": {
      "teamRank": 99,
      "currentScore": "0",
      "nameRaw": "Georgia Tech",
      "description": ""
    }
  },
  {
    "startDate": "2021-09-18T20:00Z",
    "gameState": "Scheduled",
    "id": 401282628,
    "home": {
      "teamRank": 99,
      "currentScore": "0",
      "nameRaw": "Duke",
      "description": ""
    },
    "away": {
      "teamRank": 99,
      "currentScore": "0",
      "nameRaw": "Northwestern",
      "description": ""
    }
  },
  {
    "startDate": "2021-09-18T16:00Z",
    "gameState": "Scheduled",
    "id": 401282629,
    "home": {
      "teamRank": 99,
      "currentScore": "0",
      "nameRaw": "Miami",
      "description": ""
    },
    "away": {
      "teamRank": 99,
      "currentScore": "0",
      "nameRaw": "Michigan State",
      "description": ""
    }
  },
  {
    "startDate": "2021-09-18T23:30Z",
    "gameState": "Scheduled",
    "id": 401282630,
    "home": {
      "teamRank": 99,
      "currentScore": "0",
      "nameRaw": "NC State",
      "description": ""
    },
    "away": {
      "teamRank": 99,
      "currentScore": "0",
      "nameRaw": "Furman",
      "description": ""
    }
  },
  {
    "startDate": "2021-09-18T23:30Z",
    "gameState": "Scheduled",
    "id": 401282631,
    "home": {
      "teamRank": 99,
      "currentScore": "0",
      "nameRaw": "North Carolina",
      "description": ""
    },
    "away": {
      "teamRank": 99,
      "currentScore": "0",
      "nameRaw": "Virginia",
      "description": ""
    }
  },
  {
    "startDate": "2021-09-18T16:00Z",
    "gameState": "Scheduled",
    "id": 401282632,
    "home": {
      "teamRank": 99,
      "currentScore": "0",
      "nameRaw": "Pittsburgh",
      "description": ""
    },
    "away": {
      "teamRank": 99,
      "currentScore": "0",
      "nameRaw": "Western Michigan",
      "description": ""
    }
  },
  {
    "startDate": "2021-09-18T16:00Z",
    "gameState": "Scheduled",
    "id": 401282633,
    "home": {
      "teamRank": 99,
      "currentScore": "0",
      "nameRaw": "Syracuse",
      "description": ""
    },
    "away": {
      "teamRank": 99,
      "currentScore": "0",
      "nameRaw": "Albany",
      "description": ""
    }
  },
  {
    "startDate": "2021-09-18T16:00Z",
    "gameState": "Scheduled",
    "id": 401282634,
    "home": {
      "teamRank": 99,
      "currentScore": "0",
      "nameRaw": "Temple",
      "description": ""
    },
    "away": {
      "teamRank": 99,
      "currentScore": "0",
      "nameRaw": "Boston College",
      "description": ""
    }
  },
  {
    "startDate": "2021-09-18T19:30Z",
    "gameState": "Scheduled",
    "id": 401282635,
    "home": {
      "teamRank": 99,
      "currentScore": "0",
      "nameRaw": "Wake Forest",
      "description": ""
    },
    "away": {
      "teamRank": 99,
      "currentScore": "0",
      "nameRaw": "Florida State",
      "description": ""
    }
  },
  {
    "startDate": "2021-09-18T16:00Z",
    "gameState": "Scheduled",
    "id": 401282636,
    "home": {
      "teamRank": 99,
      "currentScore": "0",
      "nameRaw": "West Virginia",
      "description": ""
    },
    "away": {
      "teamRank": 99,
      "currentScore": "0",
      "nameRaw": "Virginia Tech",
      "description": ""
    }
  },
  {
    "startDate": "2021-09-18T18:30Z",
    "gameState": "Scheduled",
    "id": 401282706,
    "home": {
      "teamRank": 99,
      "currentScore": "0",
      "nameRaw": "Notre Dame",
      "description": ""
    },
    "away": {
      "teamRank": 99,
      "currentScore": "0",
      "nameRaw": "Purdue",
      "description": ""
    }
  },
  {
    "startDate": "2021-09-18T01:00Z",
    "gameState": "Scheduled",
    "id": 401282715,
    "home": {
      "teamRank": 99,
      "currentScore": "0",
      "nameRaw": "Illinois",
      "description": ""
    },
    "away": {
      "teamRank": 99,
      "currentScore": "0",
      "nameRaw": "Maryland",
      "description": ""
    }
  },
  {
    "startDate": "2021-09-18T16:00Z",
    "gameState": "Scheduled",
    "id": 401282725,
    "home": {
      "teamRank": 99,
      "currentScore": "0",
      "nameRaw": "Indiana",
      "description": ""
    },
    "away": {
      "teamRank": 99,
      "currentScore": "0",
      "nameRaw": "Cincinnati",
      "description": ""
    }
  },
  {
    "startDate": "2021-09-18T19:30Z",
    "gameState": "Scheduled",
    "id": 401282755,
    "home": {
      "teamRank": 99,
      "currentScore": "0",
      "nameRaw": "Iowa",
      "description": ""
    },
    "away": {
      "teamRank": 99,
      "currentScore": "0",
      "nameRaw": "Kent State",
      "description": ""
    }
  },
  {
    "startDate": "2021-09-18T16:00Z",
    "gameState": "Scheduled",
    "id": 401282774,
    "home": {
      "teamRank": 99,
      "currentScore": "0",
      "nameRaw": "Michigan",
      "description": ""
    },
    "away": {
      "teamRank": 99,
      "currentScore": "0",
      "nameRaw": "Northern Illinois",
      "description": ""
    }
  },
  {
    "startDate": "2021-09-18T17:00Z",
    "gameState": "Scheduled",
    "id": 401282791,
    "home": {
      "teamRank": 99,
      "currentScore": "0",
      "nameRaw": "Colorado",
      "description": ""
    },
    "away": {
      "teamRank": 99,
      "currentScore": "0",
      "nameRaw": "Minnesota",
      "description": ""
    }
  },
  {
    "startDate": "2021-09-18T16:00Z",
    "gameState": "Scheduled",
    "id": 401282798,
    "home": {
      "teamRank": 99,
      "currentScore": "0",
      "nameRaw": "Oklahoma",
      "description": ""
    },
    "away": {
      "teamRank": 99,
      "currentScore": "0",
      "nameRaw": "Nebraska",
      "description": ""
    }
  },
  {
    "startDate": "2021-09-18T19:30Z",
    "gameState": "Scheduled",
    "id": 401282810,
    "home": {
      "teamRank": 99,
      "currentScore": "0",
      "nameRaw": "Ohio State",
      "description": ""
    },
    "away": {
      "teamRank": 99,
      "currentScore": "0",
      "nameRaw": "Tulsa",
      "description": ""
    }
  },
  {
    "startDate": "2021-09-18T19:30Z",
    "gameState": "Scheduled",
    "id": 401282823,
    "home": {
      "teamRank": 99,
      "currentScore": "0",
      "nameRaw": "Rutgers",
      "description": ""
    },
    "away": {
      "teamRank": 99,
      "currentScore": "0",
      "nameRaw": "Delaware",
      "description": ""
    }
  },
  {
    "startDate": "2021-09-18T16:00Z",
    "gameState": "Scheduled",
    "id": 401286189,
    "home": {
      "teamRank": 99,
      "currentScore": "0",
      "nameRaw": "Army",
      "description": ""
    },
    "away": {
      "teamRank": 99,
      "currentScore": "0",
      "nameRaw": "UConn",
      "description": ""
    }
  },
  {
    "startDate": "2021-09-18T19:30Z",
    "gameState": "Scheduled",
    "id": 401286300,
    "home": {
      "teamRank": 99,
      "currentScore": "0",
      "nameRaw": "UMass",
      "description": ""
    },
    "away": {
      "teamRank": 99,
      "currentScore": "0",
      "nameRaw": "Eastern Michigan",
      "description": ""
    }
  },
  {
    "startDate": "2021-09-19T01:00Z",
    "gameState": "Scheduled",
    "id": 401287903,
    "home": {
      "teamRank": 99,
      "currentScore": "0",
      "nameRaw": "Boise State",
      "description": ""
    },
    "away": {
      "teamRank": 99,
      "currentScore": "0",
      "nameRaw": "Oklahoma State",
      "description": ""
    }
  },
  {
    "startDate": "2021-09-18T19:30Z",
    "gameState": "Scheduled",
    "id": 401287904,
    "home": {
      "teamRank": 99,
      "currentScore": "0",
      "nameRaw": "Kansas",
      "description": ""
    },
    "away": {
      "teamRank": 99,
      "currentScore": "0",
      "nameRaw": "Baylor",
      "description": ""
    }
  },
  {
    "startDate": "2021-09-18T18:05Z",
    "gameState": "Scheduled",
    "id": 401287905,
    "home": {
      "teamRank": 99,
      "currentScore": "0",
      "nameRaw": "Kansas State",
      "description": ""
    },
    "away": {
      "teamRank": 99,
      "currentScore": "0",
      "nameRaw": "Nevada",
      "description": ""
    }
  },
  {
    "startDate": "2021-09-19T02:30Z",
    "gameState": "Scheduled",
    "id": 401287906,
    "home": {
      "teamRank": 99,
      "currentScore": "0",
      "nameRaw": "UNLV",
      "description": ""
    },
    "away": {
      "teamRank": 99,
      "currentScore": "0",
      "nameRaw": "Iowa State",
      "description": ""
    }
  },
  {
    "startDate": "2021-09-18T23:00Z",
    "gameState": "Scheduled",
    "id": 401301005,
    "home": {
      "teamRank": 99,
      "currentScore": "0",
      "nameRaw": "Houston",
      "description": ""
    },
    "away": {
      "teamRank": 99,
      "currentScore": "0",
      "nameRaw": "Grambling",
      "description": ""
    }
  },
  {
    "startDate": "2021-09-18T23:00Z",
    "gameState": "Scheduled",
    "id": 401301006,
    "home": {
      "teamRank": 99,
      "currentScore": "0",
      "nameRaw": "South Florida",
      "description": ""
    },
    "away": {
      "teamRank": 99,
      "currentScore": "0",
      "nameRaw": "Florida A&M",
      "description": ""
    }
  },
  {
    "startDate": "2021-09-18T19:30Z",
    "gameState": "Scheduled",
    "id": 401308843,
    "home": {
      "teamRank": 99,
      "currentScore": "0",
      "nameRaw": "Miami (OH)",
      "description": ""
    },
    "away": {
      "teamRank": 99,
      "currentScore": "0",
      "nameRaw": "Long Island University",
      "description": ""
    }
  },
  {
    "startDate": "2021-09-18T20:00Z",
    "gameState": "Scheduled",
    "id": 401309549,
    "home": {
      "teamRank": 99,
      "currentScore": "0",
      "nameRaw": "Wyoming",
      "description": ""
    },
    "away": {
      "teamRank": 99,
      "currentScore": "0",
      "nameRaw": "Ball State",
      "description": ""
    }
  },
  {
    "startDate": "2021-09-18T19:30Z",
    "gameState": "Scheduled",
    "id": 401309550,
    "home": {
      "teamRank": 99,
      "currentScore": "0",
      "nameRaw": "Akron",
      "description": ""
    },
    "away": {
      "teamRank": 99,
      "currentScore": "0",
      "nameRaw": "Bryant",
      "description": ""
    }
  },
  {
    "startDate": "2021-09-18T21:00Z",
    "gameState": "Scheduled",
    "id": 401309551,
    "home": {
      "teamRank": 99,
      "currentScore": "0",
      "nameRaw": "Bowling Green",
      "description": ""
    },
    "away": {
      "teamRank": 99,
      "currentScore": "0",
      "nameRaw": "Murray State",
      "description": ""
    }
  },
  {
    "startDate": "2021-09-18T16:00Z",
    "gameState": "Scheduled",
    "id": 401309552,
    "home": {
      "teamRank": 99,
      "currentScore": "0",
      "nameRaw": "Buffalo",
      "description": ""
    },
    "away": {
      "teamRank": 99,
      "currentScore": "0",
      "nameRaw": "Coastal Carolina",
      "description": ""
    }
  },
  {
    "startDate": "2021-09-18T20:00Z",
    "gameState": "Scheduled",
    "id": 401309553,
    "home": {
      "teamRank": 99,
      "currentScore": "0",
      "nameRaw": "Toledo",
      "description": ""
    },
    "away": {
      "teamRank": 99,
      "currentScore": "0",
      "nameRaw": "Colorado State",
      "description": ""
    }
  },
  {
    "startDate": "2021-09-18T19:30Z",
    "gameState": "Scheduled",
    "id": 401309604,
    "home": {
      "teamRank": 99,
      "currentScore": "0",
      "nameRaw": "Appalachian State",
      "description": ""
    },
    "away": {
      "teamRank": 99,
      "currentScore": "0",
      "nameRaw": "Elon",
      "description": ""
    }
  },
  {
    "startDate": "2021-09-18T20:15Z",
    "gameState": "Scheduled",
    "id": 401309605,
    "home": {
      "teamRank": 99,
      "currentScore": "0",
      "nameRaw": "Washington",
      "description": ""
    },
    "away": {
      "teamRank": 99,
      "currentScore": "0",
      "nameRaw": "Arkansas State",
      "description": ""
    }
  },
  {
    "startDate": "2021-09-17T00:00Z",
    "gameState": "Scheduled",
    "id": 401309606,
    "home": {
      "teamRank": 99,
      "currentScore": "0",
      "nameRaw": "Louisiana",
      "description": ""
    },
    "away": {
      "teamRank": 99,
      "currentScore": "0",
      "nameRaw": "Ohio",
      "description": ""
    }
  },
  {
    "startDate": "2021-09-19T00:00Z",
    "gameState": "Scheduled",
    "id": 401309607,
    "home": {
      "teamRank": 99,
      "currentScore": "0",
      "nameRaw": "UL Monroe",
      "description": ""
    },
    "away": {
      "teamRank": 99,
      "currentScore": "0",
      "nameRaw": "Jackson State",
      "description": ""
    }
  },
  {
    "startDate": "2021-09-19T00:00Z",
    "gameState": "Scheduled",
    "id": 401309608,
    "home": {
      "teamRank": 99,
      "currentScore": "0",
      "nameRaw": "South Alabama",
      "description": ""
    },
    "away": {
      "teamRank": 99,
      "currentScore": "0",
      "nameRaw": "Alcorn State",
      "description": ""
    }
  },
  {
    "startDate": "2021-09-18T23:00Z",
    "gameState": "Scheduled",
    "id": 401309609,
    "home": {
      "teamRank": 99,
      "currentScore": "0",
      "nameRaw": "Texas State",
      "description": ""
    },
    "away": {
      "teamRank": 99,
      "currentScore": "0",
      "nameRaw": "Incarnate Word",
      "description": ""
    }
  },
  {
    "startDate": "2021-09-18T20:00Z",
    "gameState": "Scheduled",
    "id": 401309849,
    "home": {
      "teamRank": 99,
      "currentScore": "0",
      "nameRaw": "California",
      "description": ""
    },
    "away": {
      "teamRank": 99,
      "currentScore": "0",
      "nameRaw": "Sacramento State",
      "description": ""
    }
  },
  {
    "startDate": "2021-09-18T23:30Z",
    "gameState": "Scheduled",
    "id": 401309850,
    "home": {
      "teamRank": 99,
      "currentScore": "0",
      "nameRaw": "Oregon",
      "description": ""
    },
    "away": {
      "teamRank": 99,
      "currentScore": "0",
      "nameRaw": "Stony Brook",
      "description": ""
    }
  },
  {
    "startDate": "2021-09-18T19:30Z",
    "gameState": "Scheduled",
    "id": 401309851,
    "home": {
      "teamRank": 99,
      "currentScore": "0",
      "nameRaw": "Oregon State",
      "description": ""
    },
    "away": {
      "teamRank": 99,
      "currentScore": "0",
      "nameRaw": "Idaho",
      "description": ""
    }
  },
  {
    "startDate": "2021-09-18T19:30Z",
    "gameState": "Scheduled",
    "id": 401309852,
    "home": {
      "teamRank": 99,
      "currentScore": "0",
      "nameRaw": "Washington State",
      "description": ""
    },
    "away": {
      "teamRank": 99,
      "currentScore": "0",
      "nameRaw": "USC",
      "description": ""
    }
  },
  {
    "startDate": "2021-09-19T02:00Z",
    "gameState": "Scheduled",
    "id": 401309853,
    "home": {
      "teamRank": 99,
      "currentScore": "0",
      "nameRaw": "Arizona",
      "description": ""
    },
    "away": {
      "teamRank": 99,
      "currentScore": "0",
      "nameRaw": "Northern Arizona",
      "description": ""
    }
  },
  {
    "startDate": "2021-09-19T02:15Z",
    "gameState": "Scheduled",
    "id": 401309854,
    "home": {
      "teamRank": 99,
      "currentScore": "0",
      "nameRaw": "BYU",
      "description": ""
    },
    "away": {
      "teamRank": 99,
      "currentScore": "0",
      "nameRaw": "Arizona State",
      "description": ""
    }
  },
  {
    "startDate": "2021-09-19T02:45Z",
    "gameState": "Scheduled",
    "id": 401309855,
    "home": {
      "teamRank": 99,
      "currentScore": "0",
      "nameRaw": "UCLA",
      "description": ""
    },
    "away": {
      "teamRank": 99,
      "currentScore": "0",
      "nameRaw": "Fresno State",
      "description": ""
    }
  },
  {
    "startDate": "2021-09-18T23:00Z",
    "gameState": "Scheduled",
    "id": 401309856,
    "home": {
      "teamRank": 99,
      "currentScore": "0",
      "nameRaw": "San Diego State",
      "description": ""
    },
    "away": {
      "teamRank": 99,
      "currentScore": "0",
      "nameRaw": "Utah",
      "description": ""
    }
  },
  {
    "startDate": "2021-09-18T23:30Z",
    "gameState": "Scheduled",
    "id": 401310704,
    "home": {
      "teamRank": 99,
      "currentScore": "0",
      "nameRaw": "Air Force",
      "description": ""
    },
    "away": {
      "teamRank": 99,
      "currentScore": "0",
      "nameRaw": "Utah State",
      "description": ""
    }
  },
  {
    "startDate": "2021-09-19T04:30Z",
    "gameState": "Scheduled",
    "id": 401310705,
    "home": {
      "teamRank": 99,
      "currentScore": "0",
      "nameRaw": "Hawai'i",
      "description": ""
    },
    "away": {
      "teamRank": 99,
      "currentScore": "0",
      "nameRaw": "San José State",
      "description": ""
    }
  },
  {
    "startDate": "2021-09-19T00:00Z",
    "gameState": "Scheduled",
    "id": 401319455,
    "home": {
      "teamRank": 99,
      "currentScore": "0",
      "nameRaw": "New Mexico State",
      "description": ""
    },
    "away": {
      "teamRank": 99,
      "currentScore": "0",
      "nameRaw": "South Carolina State",
      "description": ""
    }
  }
]
