[
  {
    "startDate": "2019-10-26T23:00Z",
    "gameState": "Scheduled",
    "id": 401110831,
    "home": {
      "teamRank": 99,
      "currentScore": "0",
      "nameRaw": "Alabama",
      "description": ""
    },
    "away": {
      "teamRank": 99,
      "currentScore": "0",
      "nameRaw": "Arkansas",
      "description": ""
    }
  },
  {
    "startDate": "2019-10-26T23:30Z",
    "gameState": "Scheduled",
    "id": 401110832,
    "home": {
      "teamRank": 99,
      "currentScore": "0",
      "nameRaw": "Kentucky",
      "description": ""
    },
    "away": {
      "teamRank": 99,
      "currentScore": "0",
      "nameRaw": "Missouri",
      "description": ""
    }
  },
  {
    "startDate": "2019-10-26T19:30Z",
    "gameState": "Scheduled",
    "id": 401110833,
    "home": {
      "teamRank": 99,
      "currentScore": "0",
      "nameRaw": "LSU",
      "description": ""
    },
    "away": {
      "teamRank": 99,
      "currentScore": "0",
      "nameRaw": "Auburn",
      "description": ""
    }
  },
  {
    "startDate": "2019-10-26T20:00Z",
    "gameState": "Scheduled",
    "id": 401110834,
    "home": {
      "teamRank": 99,
      "currentScore": "0",
      "nameRaw": "Tennessee",
      "description": ""
    },
    "away": {
      "teamRank": 99,
      "currentScore": "0",
      "nameRaw": "South Carolina",
      "description": ""
    }
  },
  {
    "startDate": "2019-10-26T16:00Z",
    "gameState": "Scheduled",
    "id": 401110835,
    "home": {
      "teamRank": 99,
      "currentScore": "0",
      "nameRaw": "Texas A&M",
      "description": ""
    },
    "away": {
      "teamRank": 99,
      "currentScore": "0",
      "nameRaw": "Mississippi State",
      "description": ""
    }
  },
  {
    "startDate": "2019-10-26T19:30Z",
    "gameState": "Scheduled",
    "id": 401112091,
    "home": {
      "teamRank": 99,
      "currentScore": "0",
      "nameRaw": "Iowa State",
      "description": ""
    },
    "away": {
      "teamRank": 99,
      "currentScore": "0",
      "nameRaw": "Oklahoma State",
      "description": ""
    }
  },
  {
    "startDate": "2019-10-26T23:00Z",
    "gameState": "Scheduled",
    "id": 401112103,
    "home": {
      "teamRank": 99,
      "currentScore": "0",
      "nameRaw": "Kansas",
      "description": ""
    },
    "away": {
      "teamRank": 99,
      "currentScore": "0",
      "nameRaw": "Texas Tech",
      "description": ""
    }
  },
  {
    "startDate": "2019-10-26T16:00Z",
    "gameState": "Scheduled",
    "id": 401112110,
    "home": {
      "teamRank": 99,
      "currentScore": "0",
      "nameRaw": "Kansas State",
      "description": ""
    },
    "away": {
      "teamRank": 99,
      "currentScore": "0",
      "nameRaw": "Oklahoma",
      "description": ""
    }
  },
  {
    "startDate": "2019-10-26T19:30Z",
    "gameState": "Scheduled",
    "id": 401112132,
    "home": {
      "teamRank": 99,
      "currentScore": "0",
      "nameRaw": "TCU",
      "description": ""
    },
    "away": {
      "teamRank": 99,
      "currentScore": "0",
      "nameRaw": "Texas",
      "description": ""
    }
  },
  {
    "startDate": "2019-10-26T16:00Z",
    "gameState": "Scheduled",
    "id": 401112152,
    "home": {
      "teamRank": 99,
      "currentScore": "0",
      "nameRaw": "Purdue",
      "description": ""
    },
    "away": {
      "teamRank": 99,
      "currentScore": "0",
      "nameRaw": "Illinois",
      "description": ""
    }
  },
  {
    "startDate": "2019-10-26T19:30Z",
    "gameState": "Scheduled",
    "id": 401112164,
    "home": {
      "teamRank": 99,
      "currentScore": "0",
      "nameRaw": "Nebraska",
      "description": ""
    },
    "away": {
      "teamRank": 99,
      "currentScore": "0",
      "nameRaw": "Indiana",
      "description": ""
    }
  },
  {
    "startDate": "2019-10-26T16:00Z",
    "gameState": "Scheduled",
    "id": 401112197,
    "home": {
      "teamRank": 99,
      "currentScore": "0",
      "nameRaw": "Northwestern",
      "description": ""
    },
    "away": {
      "teamRank": 99,
      "currentScore": "0",
      "nameRaw": "Iowa",
      "description": ""
    }
  },
  {
    "startDate": "2019-10-26T19:30Z",
    "gameState": "Scheduled",
    "id": 401112207,
    "home": {
      "teamRank": 99,
      "currentScore": "0",
      "nameRaw": "Minnesota",
      "description": ""
    },
    "away": {
      "teamRank": 99,
      "currentScore": "0",
      "nameRaw": "Maryland",
      "description": ""
    }
  },
  {
    "startDate": "2019-10-26T19:30Z",
    "gameState": "Scheduled",
    "id": 401112218,
    "home": {
      "teamRank": 99,
      "currentScore": "0",
      "nameRaw": "Michigan State",
      "description": ""
    },
    "away": {
      "teamRank": 99,
      "currentScore": "0",
      "nameRaw": "Penn State",
      "description": ""
    }
  },
  {
    "startDate": "2019-10-26T23:30Z",
    "gameState": "Scheduled",
    "id": 401112227,
    "home": {
      "teamRank": 99,
      "currentScore": "0",
      "nameRaw": "Michigan",
      "description": ""
    },
    "away": {
      "teamRank": 99,
      "currentScore": "0",
      "nameRaw": "Notre Dame",
      "description": ""
    }
  },
  {
    "startDate": "2019-10-26T16:00Z",
    "gameState": "Scheduled",
    "id": 401112254,
    "home": {
      "teamRank": 99,
      "currentScore": "0",
      "nameRaw": "Ohio State",
      "description": ""
    },
    "away": {
      "teamRank": 99,
      "currentScore": "0",
      "nameRaw": "Wisconsin",
      "description": ""
    }
  },
  {
    "startDate": "2019-10-26T16:00Z",
    "gameState": "Scheduled",
    "id": 401112266,
    "home": {
      "teamRank": 99,
      "currentScore": "0",
      "nameRaw": "Rutgers",
      "description": ""
    },
    "away": {
      "teamRank": 99,
      "currentScore": "0",
      "nameRaw": "Liberty",
      "description": ""
    }
  },
  {
    "startDate": "2019-10-26T23:30Z",
    "gameState": "Scheduled",
    "id": 401112490,
    "home": {
      "teamRank": 99,
      "currentScore": "0",
      "nameRaw": "Clemson",
      "description": ""
    },
    "away": {
      "teamRank": 99,
      "currentScore": "0",
      "nameRaw": "Boston College",
      "description": ""
    }
  },
  {
    "startDate": "2019-10-26T20:00Z",
    "gameState": "Scheduled",
    "id": 401112491,
    "home": {
      "teamRank": 99,
      "currentScore": "0",
      "nameRaw": "North Carolina",
      "description": ""
    },
    "away": {
      "teamRank": 99,
      "currentScore": "0",
      "nameRaw": "Duke",
      "description": ""
    }
  },
  {
    "startDate": "2019-10-26T19:30Z",
    "gameState": "Scheduled",
    "id": 401112492,
    "home": {
      "teamRank": 99,
      "currentScore": "0",
      "nameRaw": "Florida State",
      "description": ""
    },
    "away": {
      "teamRank": 99,
      "currentScore": "0",
      "nameRaw": "Syracuse",
      "description": ""
    }
  },
  {
    "startDate": "2019-10-26T19:30Z",
    "gameState": "Scheduled",
    "id": 401112493,
    "home": {
      "teamRank": 99,
      "currentScore": "0",
      "nameRaw": "Louisville",
      "description": ""
    },
    "away": {
      "teamRank": 99,
      "currentScore": "0",
      "nameRaw": "Virginia",
      "description": ""
    }
  },
  {
    "startDate": "2019-10-26T16:00Z",
    "gameState": "Scheduled",
    "id": 401112494,
    "home": {
      "teamRank": 99,
      "currentScore": "0",
      "nameRaw": "Pittsburgh",
      "description": ""
    },
    "away": {
      "teamRank": 99,
      "currentScore": "0",
      "nameRaw": "Miami",
      "description": ""
    }
  },
  {
    "startDate": "2019-10-26T23:30Z",
    "gameState": "Scheduled",
    "id": 401114159,
    "home": {
      "teamRank": 99,
      "currentScore": "0",
      "nameRaw": "UCLA",
      "description": ""
    },
    "away": {
      "teamRank": 99,
      "currentScore": "0",
      "nameRaw": "Arizona State",
      "description": ""
    }
  },
  {
    "startDate": "2019-10-26T19:30Z",
    "gameState": "Scheduled",
    "id": 401114170,
    "home": {
      "teamRank": 99,
      "currentScore": "0",
      "nameRaw": "Stanford",
      "description": ""
    },
    "away": {
      "teamRank": 99,
      "currentScore": "0",
      "nameRaw": "Arizona",
      "description": ""
    }
  },
  {
    "startDate": "2019-10-27T02:00Z",
    "gameState": "Scheduled",
    "id": 401114179,
    "home": {
      "teamRank": 99,
      "currentScore": "0",
      "nameRaw": "Utah",
      "description": ""
    },
    "away": {
      "teamRank": 99,
      "currentScore": "0",
      "nameRaw": "California",
      "description": ""
    }
  },
  {
    "startDate": "2019-10-26T01:00Z",
    "gameState": "Scheduled",
    "id": 401114188,
    "home": {
      "teamRank": 99,
      "currentScore": "0",
      "nameRaw": "Colorado",
      "description": ""
    },
    "away": {
      "teamRank": 99,
      "currentScore": "0",
      "nameRaw": "USC",
      "description": ""
    }
  },
  {
    "startDate": "2019-10-27T02:30Z",
    "gameState": "Scheduled",
    "id": 401114197,
    "home": {
      "teamRank": 99,
      "currentScore": "0",
      "nameRaw": "Oregon",
      "description": ""
    },
    "away": {
      "teamRank": 99,
      "currentScore": "0",
      "nameRaw": "Washington State",
      "description": ""
    }
  },
  {
    "startDate": "2019-10-26T19:30Z",
    "gameState": "Scheduled",
    "id": 401114293,
    "home": {
      "teamRank": 99,
      "currentScore": "0",
      "nameRaw": "Charlotte",
      "description": ""
    },
    "away": {
      "teamRank": 99,
      "currentScore": "0",
      "nameRaw": "North Texas",
      "description": ""
    }
  },
  {
    "startDate": "2019-10-26T19:30Z",
    "gameState": "Scheduled",
    "id": 401114294,
    "home": {
      "teamRank": 99,
      "currentScore": "0",
      "nameRaw": "Middle Tennessee",
      "description": ""
    },
    "away": {
      "teamRank": 99,
      "currentScore": "0",
      "nameRaw": "Florida International",
      "description": ""
    }
  },
  {
    "startDate": "2019-10-26T19:30Z",
    "gameState": "Scheduled",
    "id": 401114295,
    "home": {
      "teamRank": 99,
      "currentScore": "0",
      "nameRaw": "Old Dominion",
      "description": ""
    },
    "away": {
      "teamRank": 99,
      "currentScore": "0",
      "nameRaw": "Florida Atlantic",
      "description": ""
    }
  },
  {
    "startDate": "2019-10-27T00:00Z",
    "gameState": "Scheduled",
    "id": 401114296,
    "home": {
      "teamRank": 99,
      "currentScore": "0",
      "nameRaw": "UTEP",
      "description": ""
    },
    "away": {
      "teamRank": 99,
      "currentScore": "0",
      "nameRaw": "Louisiana Tech",
      "description": ""
    }
  },
  {
    "startDate": "2019-10-26T18:30Z",
    "gameState": "Scheduled",
    "id": 401114297,
    "home": {
      "teamRank": 99,
      "currentScore": "0",
      "nameRaw": "Marshall",
      "description": ""
    },
    "away": {
      "teamRank": 99,
      "currentScore": "0",
      "nameRaw": "Western Kentucky",
      "description": ""
    }
  },
  {
    "startDate": "2019-10-26T17:00Z",
    "gameState": "Scheduled",
    "id": 401114298,
    "home": {
      "teamRank": 99,
      "currentScore": "0",
      "nameRaw": "Rice",
      "description": ""
    },
    "away": {
      "teamRank": 99,
      "currentScore": "0",
      "nameRaw": "Southern Mississippi",
      "description": ""
    }
  },
  {
    "startDate": "2019-10-26T16:00Z",
    "gameState": "Scheduled",
    "id": 401114330,
    "home": {
      "teamRank": 99,
      "currentScore": "0",
      "nameRaw": "Army",
      "description": ""
    },
    "away": {
      "teamRank": 99,
      "currentScore": "0",
      "nameRaw": "San Jose State",
      "description": ""
    }
  },
  {
    "startDate": "2019-10-26T19:00Z",
    "gameState": "Scheduled",
    "id": 401114344,
    "home": {
      "teamRank": 99,
      "currentScore": "0",
      "nameRaw": "Georgia Southern",
      "description": ""
    },
    "away": {
      "teamRank": 99,
      "currentScore": "0",
      "nameRaw": "New Mexico State",
      "description": ""
    }
  },
  {
    "startDate": "2019-10-26T19:30Z",
    "gameState": "Scheduled",
    "id": 401114357,
    "home": {
      "teamRank": 99,
      "currentScore": "0",
      "nameRaw": "UMass",
      "description": ""
    },
    "away": {
      "teamRank": 99,
      "currentScore": "0",
      "nameRaw": "UConn",
      "description": ""
    }
  },
  {
    "startDate": "2019-10-27T02:15Z",
    "gameState": "Scheduled",
    "id": 401117530,
    "home": {
      "teamRank": 99,
      "currentScore": "0",
      "nameRaw": "Air Force",
      "description": ""
    },
    "away": {
      "teamRank": 99,
      "currentScore": "0",
      "nameRaw": "Utah State",
      "description": ""
    }
  },
  {
    "startDate": "2019-10-26T23:30Z",
    "gameState": "Scheduled",
    "id": 401117531,
    "home": {
      "teamRank": 99,
      "currentScore": "0",
      "nameRaw": "Fresno State",
      "description": ""
    },
    "away": {
      "teamRank": 99,
      "currentScore": "0",
      "nameRaw": "Colorado State",
      "description": ""
    }
  },
  {
    "startDate": "2019-10-26T20:00Z",
    "gameState": "Scheduled",
    "id": 401117532,
    "home": {
      "teamRank": 99,
      "currentScore": "0",
      "nameRaw": "New Mexico",
      "description": ""
    },
    "away": {
      "teamRank": 99,
      "currentScore": "0",
      "nameRaw": "Hawai'i",
      "description": ""
    }
  },
  {
    "startDate": "2019-10-26T18:00Z",
    "gameState": "Scheduled",
    "id": 401117533,
    "home": {
      "teamRank": 99,
      "currentScore": "0",
      "nameRaw": "Wyoming",
      "description": ""
    },
    "away": {
      "teamRank": 99,
      "currentScore": "0",
      "nameRaw": "Nevada",
      "description": ""
    }
  },
  {
    "startDate": "2019-10-27T02:30Z",
    "gameState": "Scheduled",
    "id": 401117534,
    "home": {
      "teamRank": 99,
      "currentScore": "0",
      "nameRaw": "UNLV",
      "description": ""
    },
    "away": {
      "teamRank": 99,
      "currentScore": "0",
      "nameRaw": "San Diego State",
      "description": ""
    }
  },
  {
    "startDate": "2019-10-24T23:30Z",
    "gameState": "Scheduled",
    "id": 401117889,
    "home": {
      "teamRank": 99,
      "currentScore": "0",
      "nameRaw": "Houston",
      "description": ""
    },
    "away": {
      "teamRank": 99,
      "currentScore": "0",
      "nameRaw": "SMU",
      "description": ""
    }
  },
  {
    "startDate": "2019-10-26T19:30Z",
    "gameState": "Scheduled",
    "id": 401117890,
    "home": {
      "teamRank": 99,
      "currentScore": "0",
      "nameRaw": "Navy",
      "description": ""
    },
    "away": {
      "teamRank": 99,
      "currentScore": "0",
      "nameRaw": "Tulane",
      "description": ""
    }
  },
  {
    "startDate": "2019-10-26T23:00Z",
    "gameState": "Scheduled",
    "id": 401117891,
    "home": {
      "teamRank": 99,
      "currentScore": "0",
      "nameRaw": "Temple",
      "description": ""
    },
    "away": {
      "teamRank": 99,
      "currentScore": "0",
      "nameRaw": "UCF",
      "description": ""
    }
  },
  {
    "startDate": "2019-10-26T19:45Z",
    "gameState": "Scheduled",
    "id": 401117892,
    "home": {
      "teamRank": 99,
      "currentScore": "0",
      "nameRaw": "East Carolina",
      "description": ""
    },
    "away": {
      "teamRank": 99,
      "currentScore": "0",
      "nameRaw": "South Florida",
      "description": ""
    }
  },
  {
    "startDate": "2019-10-26T23:00Z",
    "gameState": "Scheduled",
    "id": 401117893,
    "home": {
      "teamRank": 99,
      "currentScore": "0",
      "nameRaw": "Tulsa",
      "description": ""
    },
    "away": {
      "teamRank": 99,
      "currentScore": "0",
      "nameRaw": "Memphis",
      "description": ""
    }
  },
  {
    "startDate": "2019-10-26T19:30Z",
    "gameState": "Scheduled",
    "id": 401119287,
    "home": {
      "teamRank": 99,
      "currentScore": "0",
      "nameRaw": "Northern Illinois",
      "description": ""
    },
    "away": {
      "teamRank": 99,
      "currentScore": "0",
      "nameRaw": "Akron",
      "description": ""
    }
  },
  {
    "startDate": "2019-10-26T16:00Z",
    "gameState": "Scheduled",
    "id": 401119288,
    "home": {
      "teamRank": 99,
      "currentScore": "0",
      "nameRaw": "Western Michigan",
      "description": ""
    },
    "away": {
      "teamRank": 99,
      "currentScore": "0",
      "nameRaw": "Bowling Green",
      "description": ""
    }
  },
  {
    "startDate": "2019-10-26T19:30Z",
    "gameState": "Scheduled",
    "id": 401119289,
    "home": {
      "teamRank": 99,
      "currentScore": "0",
      "nameRaw": "Buffalo",
      "description": ""
    },
    "away": {
      "teamRank": 99,
      "currentScore": "0",
      "nameRaw": "Central Michigan",
      "description": ""
    }
  },
  {
    "startDate": "2019-10-26T19:30Z",
    "gameState": "Scheduled",
    "id": 401119290,
    "home": {
      "teamRank": 99,
      "currentScore": "0",
      "nameRaw": "Toledo",
      "description": ""
    },
    "away": {
      "teamRank": 99,
      "currentScore": "0",
      "nameRaw": "Eastern Michigan",
      "description": ""
    }
  },
  {
    "startDate": "2019-10-26T19:30Z",
    "gameState": "Scheduled",
    "id": 401119291,
    "home": {
      "teamRank": 99,
      "currentScore": "0",
      "nameRaw": "Kent State",
      "description": ""
    },
    "away": {
      "teamRank": 99,
      "currentScore": "0",
      "nameRaw": "Miami (OH)",
      "description": ""
    }
  },
  {
    "startDate": "2019-10-26T18:00Z",
    "gameState": "Scheduled",
    "id": 401119292,
    "home": {
      "teamRank": 99,
      "currentScore": "0",
      "nameRaw": "Ball State",
      "description": ""
    },
    "away": {
      "teamRank": 99,
      "currentScore": "0",
      "nameRaw": "Ohio",
      "description": ""
    }
  },
  {
    "startDate": "2019-10-26T16:00Z",
    "gameState": "Scheduled",
    "id": 401121957,
    "home": {
      "teamRank": 99,
      "currentScore": "0",
      "nameRaw": "South Alabama",
      "description": ""
    },
    "away": {
      "teamRank": 99,
      "currentScore": "0",
      "nameRaw": "Appalachian State",
      "description": ""
    }
  },
  {
    "startDate": "2019-10-26T23:00Z",
    "gameState": "Scheduled",
    "id": 401121958,
    "home": {
      "teamRank": 99,
      "currentScore": "0",
      "nameRaw": "Arkansas State",
      "description": ""
    },
    "away": {
      "teamRank": 99,
      "currentScore": "0",
      "nameRaw": "Texas State",
      "description": ""
    }
  },
  {
    "startDate": "2019-10-26T23:00Z",
    "gameState": "Scheduled",
    "id": 401121959,
    "home": {
      "teamRank": 99,
      "currentScore": "0",
      "nameRaw": "Georgia State",
      "description": ""
    },
    "away": {
      "teamRank": 99,
      "currentScore": "0",
      "nameRaw": "Troy",
      "description": ""
    }
  }
]
